unbelipy/__init__.py
unbelipy/client.py
unbelipy/constants.py
unbelipy/errors.py
unbelipy/objects.py
unbelipy/rate_limits.py
unbelipy-2.1.1b0.dist-info/WHEEL
unbelipy-2.1.1b0.dist-info/METADATA
unbelipy-2.1.1b0.dist-info/RECORD
