Metadata-Version: 2.1
Name: unbelipy
Version: 2.1.1b0
Summary: Asynchronous wrapper for UnbelievaBoat's API written in Python.
Home-page: https://github.com/chrisdewa/unbelipy
License: MIT
Keywords: discord,discord.py,discord bot,UnbelievaBoat
Author: chrisdewa
Author-email: alexdewa@gmail.com
Requires-Python: >=3.8,<4.0
Classifier: Development Status :: 4 - Beta
Classifier: Intended Audience :: Developers
Classifier: License :: OSI Approved :: MIT License
Classifier: Programming Language :: Python :: 3
Classifier: Programming Language :: Python :: 3.10
Classifier: Programming Language :: Python :: 3.8
Classifier: Programming Language :: Python :: 3.9
Provides-Extra: docs
Requires-Dist: aiohttp (>=3.7.4.post0,<4.0.0)
Requires-Dist: aiolimiter (>=1.0.0b1,<2.0.0)
Requires-Dist: sphinx (>=4.0.0,<5.0.0); extra == "docs"
Requires-Dist: sphinx-book-theme (>=0.3.2,<0.4.0); extra == "docs"
Project-URL: Documentation, https://unbelipy.readthedocs.io/en/latest/
Project-URL: Issue tracker, https://github.com/chrisdewa/unbelipy/issues
Project-URL: Repository, https://github.com/chrisdewa/unbelipy
